{"root":"0:0:1880","crate_version":"1.0.10","includes_private":false,"index":{"0:30:1836":{"id":"0:30:1836","crate_id":0,"name":"Sealed","span":{"filename":"src/lib.rs","begin":[110,4],"end":[113,5]},"visibility":"public","docs":null,"links":{},"attrs":[],"deprecation":null,"inner":{"trait":{"is_auto":false,"is_unsafe":false,"is_object_safe":false,"items":["0:31:1823","0:32:1834"],"generics":{"params":[],"where_predicates":[]},"bounds":[{"trait_bound":{"trait":{"name":"Copy","id":"1:2990:119","args":{"angle_bracketed":{"args":[],"bindings":[]}}},"generic_params":[],"modifier":"none"}}],"implementations":[]}}},"b:1:2772-0:14:1823":{"id":"b:1:2772-0:14:1823","crate_id":0,"name":null,"span":null,"visibility":"default","docs":null,"links":{},"attrs":[],"deprecation":null,"inner":{"impl":{"is_unsafe":false,"generics":{"params":[{"name":"T","kind":{"type":{"bounds":[],"default":null,"synthetic":false}}},{"name":"U","kind":{"type":{"bounds":[],"default":null,"synthetic":false}}}],"where_predicates":[{"bound_predicate":{"type":{"generic":"U"},"bounds":[{"trait_bound":{"trait":{"name":"From","id":"1:2749:145","args":{"angle_bracketed":{"args":[{"type":{"generic":"T"}}],"bindings":[]}}},"generic_params":[],"modifier":"none"}}],"generic_params":[]}}]},"provided_trait_methods":[],"trait":{"name":"Into","id":"1:2746:163","args":{"angle_bracketed":{"args":[{"type":{"generic":"U"}}],"bindings":[]}}},"for":{"resolved_path":{"name":"Buffer","id":"0:14:1823","args":{"angle_bracketed":{"args":[],"bindings":[]}}}},"items":["1:2775:2215"],"negative":false,"synthetic":false,"blanket_impl":{"generic":"T"}}}},"0:100":{"id":"0:100","crate_id":0,"name":null,"span":{"filename":"src/lib.rs","begin":[225,0],"end":[225,64]},"visibility":"default","docs":null,"links":{},"attrs":[],"deprecation":null,"inner":{"impl":{"is_unsafe":false,"generics":{"params":[],"where_predicates":[]},"provided_trait_methods":[],"trait":{"name":"Integer","id":"0:28:1833","args":{"angle_bracketed":{"args":[],"bindings":[]}}},"for":{"primitive":"usize"},"items":[],"negative":false,"synthetic":false,"blanket_impl":null}}},"0:106":{"id":"0:106","crate_id":0,"name":null,"span":{"filename":"src/lib.rs","begin":[295,0],"end":[295,60]},"visibility":"default","docs":null,"links":{},"attrs":[],"deprecation":null,"inner":{"impl":{"is_unsafe":false,"generics":{"params":[],"where_predicates":[]},"provided_trait_methods":[],"trait":{"name":"Integer","id":"0:28:1833","args":{"angle_bracketed":{"args":[],"bindings":[]}}},"for":{"primitive":"i128"},"items":[],"negative":false,"synthetic":false,"blanket_impl":null}}},"a:1:32761:237-0:14:1823":{"id":"a:1:32761:237-0:14:1823","crate_id":0,"name":null,"span":null,"visibility":"default","docs":null,"links":{},"attrs":[],"deprecation":null,"inner":{"impl":{"is_unsafe":false,"generics":{"params":[],"where_predicates":[]},"provided_trait_methods":[],"trait":{"name":"Send","id":"1:32761:237","args":{"angle_bracketed":{"args":[],"bindings":[]}}},"for":{"resolved_path":{"name":"Buffer","id":"0:14:1823","args":{"angle_bracketed":{"args":[],"bindings":[]}}}},"items":[],"negative":false,"synthetic":true,"blanket_impl":null}}},"0:0:1880":{"id":"0:0:1880","crate_id":0,"name":"itoa","span":{"filename":"src/lib.rs","begin":[1,0],"end":[295,61]},"visibility":"public","docs":"[![github]](https://github.com/dtolnay/itoa)&ensp;[![crates-io]](https://crates.io/crates/itoa)&ensp;[![docs-rs]](https://docs.rs/itoa)\n\n[github]: https://img.shields.io/badge/github-8da0cb?style=for-the-badge&labelColor=555555&logo=github\n[crates-io]: https://img.shields.io/badge/crates.io-fc8d62?style=for-the-badge&labelColor=555555&logo=rust\n[docs-rs]: https://img.shields.io/badge/docs.rs-66c2a5?style=for-the-badge&labelColor=555555&logo=docs.rs\n\n<br>\n\nThis crate provides a fast conversion of integer primitives to decimal\nstrings. The implementation comes straight from [libcore] but avoids the\nperformance penalty of going through [`core::fmt::Formatter`].\n\nSee also [`ryu`] for printing floating point primitives.\n\n[libcore]: https://github.com/rust-lang/rust/blob/b8214dc6c6fc20d0a660fb5700dca9ebf51ebe89/src/libcore/fmt/num.rs#L201-L254\n[`core::fmt::Formatter`]: https://doc.rust-lang.org/std/fmt/struct.Formatter.html\n[`ryu`]: https://github.com/dtolnay/ryu\n\n# Example\n\n```\nfn main() {\n    let mut buffer = itoa::Buffer::new();\n    let printed = buffer.format(128u64);\n    assert_eq!(printed, \"128\");\n}\n```\n\n# Performance (lower is better)\n\n![performance](https://raw.githubusercontent.com/dtolnay/itoa/master/performance.png)","links":{},"attrs":["#![doc(html_root_url = \"https://docs.rs/itoa/1.0.10\")]","#![no_std]","#![allow(clippy::cast_lossless, clippy::cast_possible_truncation,\nclippy::expl_impl_clone_on_copy, clippy::must_use_candidate,\nclippy::needless_doctest_main, clippy::unreadable_literal)]"],"deprecation":null,"inner":{"module":{"is_crate":true,"items":["0:14:1823","0:28:1833"],"is_stripped":false}}},"0:20":{"id":"0:20","crate_id":0,"name":null,"span":{"filename":"src/lib.rs","begin":[74,0],"end":[80,1]},"visibility":"default","docs":null,"links":{},"attrs":[],"deprecation":null,"inner":{"impl":{"is_unsafe":false,"generics":{"params":[],"where_predicates":[]},"provided_trait_methods":["clone_from"],"trait":{"name":"Clone","id":"1:2485:114","args":{"angle_bracketed":{"args":[],"bindings":[]}}},"for":{"resolved_path":{"name":"Buffer","id":"0:14:1823","args":{"angle_bracketed":{"args":[],"bindings":[]}}}},"items":["0:21:458"],"negative":false,"synthetic":false,"blanket_impl":null}}},"b:1:2472-0:14:1823":{"id":"b:1:2472-0:14:1823","crate_id":0,"name":null,"span":null,"visibility":"default","docs":null,"links":{},"attrs":[],"deprecation":null,"inner":{"impl":{"is_unsafe":false,"generics":{"params":[{"name":"T","kind":{"type":{"bounds":[],"default":null,"synthetic":false}}}],"where_predicates":[{"bound_predicate":{"type":{"generic":"T"},"bounds":[{"trait_bound":{"trait":{"name":"Sized","id":"1:32762:2140","args":{"angle_bracketed":{"args":[],"bindings":[]}}},"generic_params":[],"modifier":"maybe"}}],"generic_params":[]}}]},"provided_trait_methods":[],"trait":{"name":"BorrowMut","id":"1:2466:104","args":{"angle_bracketed":{"args":[{"type":{"generic":"T"}}],"bindings":[]}}},"for":{"resolved_path":{"name":"Buffer","id":"0:14:1823","args":{"angle_bracketed":{"args":[],"bindings":[]}}}},"items":["1:2474:9265"],"negative":false,"synthetic":false,"blanket_impl":{"generic":"T"}}}},"b:1:2469-0:14:1823":{"id":"b:1:2469-0:14:1823","crate_id":0,"name":null,"span":null,"visibility":"default","docs":null,"links":{},"attrs":[],"deprecation":null,"inner":{"impl":{"is_unsafe":false,"generics":{"params":[{"name":"T","kind":{"type":{"bounds":[],"default":null,"synthetic":false}}}],"where_predicates":[{"bound_predicate":{"type":{"generic":"T"},"bounds":[{"trait_bound":{"trait":{"name":"Sized","id":"1:32762:2140","args":{"angle_bracketed":{"args":[],"bindings":[]}}},"generic_params":[],"modifier":"maybe"}}],"generic_params":[]}}]},"provided_trait_methods":[],"trait":{"name":"Borrow","id":"1:2463:103","args":{"angle_bracketed":{"args":[{"type":{"generic":"T"}}],"bindings":[]}}},"for":{"resolved_path":{"name":"Buffer","id":"0:14:1823","args":{"angle_bracketed":{"args":[],"bindings":[]}}}},"items":["1:2471:2022"],"negative":false,"synthetic":false,"blanket_impl":{"generic":"T"}}}},"1:2785:138":{"id":"1:2785:138","crate_id":1,"name":"Error","span":null,"visibility":"default","docs":null,"links":{},"attrs":[],"deprecation":null,"inner":{"assoc_type":{"generics":{"params":[],"where_predicates":[]},"bounds":[],"default":{"qualified_path":{"name":"Error","args":{"angle_bracketed":{"args":[],"bindings":[]}},"self_type":{"generic":"U"},"trait":{"name":"TryFrom","id":"1:2756:256","args":{"angle_bracketed":{"args":[{"type":{"generic":"T"}}],"bindings":[]}}}}}}}},"1:2786:1631":{"id":"1:2786:1631","crate_id":1,"name":"try_into","span":null,"visibility":"default","docs":null,"links":{},"attrs":[],"deprecation":null,"inner":{"function":{"decl":{"inputs":[["self",{"generic":"Self"}]],"output":{"resolved_path":{"name":"Result","id":"1:42415:226","args":{"angle_bracketed":{"args":[{"type":{"generic":"U"}},{"type":{"qualified_path":{"name":"Error","args":{"angle_bracketed":{"args":[],"bindings":[]}},"self_type":{"generic":"U"},"trait":{"name":"TryFrom","id":"1:2756:256","args":{"angle_bracketed":{"args":[{"type":{"generic":"T"}}],"bindings":[]}}}}}}],"bindings":[]}}}},"c_variadic":false},"generics":{"params":[],"where_predicates":[]},"header":{"const":false,"unsafe":false,"async":false,"abi":"Rust"},"has_body":true}}},"b:1:2776-0:14:1823":{"id":"b:1:2776-0:14:1823","crate_id":0,"name":null,"span":null,"visibility":"default","docs":null,"links":{},"attrs":[],"deprecation":null,"inner":{"impl":{"is_unsafe":false,"generics":{"params":[{"name":"T","kind":{"type":{"bounds":[],"default":null,"synthetic":false}}}],"where_predicates":[]},"provided_trait_methods":[],"trait":{"name":"From","id":"1:2749:145","args":{"angle_bracketed":{"args":[{"type":{"generic":"T"}}],"bindings":[]}}},"for":{"resolved_path":{"name":"Buffer","id":"0:14:1823","args":{"angle_bracketed":{"args":[],"bindings":[]}}}},"items":["1:2778:751"],"negative":false,"synthetic":false,"blanket_impl":{"generic":"T"}}}},"0:22":{"id":"0:22","crate_id":0,"name":null,"span":{"filename":"src/lib.rs","begin":[82,0],"end":[101,1]},"visibility":"default","docs":null,"links":{},"attrs":[],"deprecation":null,"inner":{"impl":{"is_unsafe":false,"generics":{"params":[],"where_predicates":[]},"provided_trait_methods":[],"trait":null,"for":{"resolved_path":{"name":"Buffer","id":"0:14:1823","args":{"angle_bracketed":{"args":[],"bindings":[]}}}},"items":["0:23:1048","0:25:736"],"negative":false,"synthetic":false,"blanket_impl":null}}},"1:2775:2215":{"id":"1:2775:2215","crate_id":1,"name":"into","span":null,"visibility":"default","docs":"Calls `U::from(self)`.\n\nThat is, this conversion is whatever the implementation of\n<code>[From]&lt;T&gt; for U</code> chooses to do.","links":{"From":"1:2749:145"},"attrs":["#[track_caller]"],"deprecation":null,"inner":{"function":{"decl":{"inputs":[["self",{"generic":"Self"}]],"output":{"generic":"U"},"c_variadic":false},"generics":{"params":[],"where_predicates":[]},"header":{"const":false,"unsafe":false,"async":false,"abi":"Rust"},"has_body":true}}},"0:18:60":{"id":"0:18:60","crate_id":0,"name":"default","span":{"filename":"src/lib.rs","begin":[67,4],"end":[69,5]},"visibility":"default","docs":null,"links":{},"attrs":["#[inline]"],"deprecation":null,"inner":{"function":{"decl":{"inputs":[],"output":{"resolved_path":{"name":"Buffer","id":"0:14:1823","args":{"angle_bracketed":{"args":[],"bindings":[]}}}},"c_variadic":false},"generics":{"params":[],"where_predicates":[]},"header":{"const":false,"unsafe":false,"async":false,"abi":"Rust"},"has_body":true}}},"1:2778:751":{"id":"1:2778:751","crate_id":1,"name":"from","span":null,"visibility":"default","docs":"Returns the argument unchanged.","links":{},"attrs":[],"deprecation":null,"inner":{"function":{"decl":{"inputs":[["t",{"generic":"T"}]],"output":{"generic":"T"},"c_variadic":false},"generics":{"params":[],"where_predicates":[]},"header":{"const":false,"unsafe":false,"async":false,"abi":"Rust"},"has_body":true}}},"1:2790:138":{"id":"1:2790:138","crate_id":1,"name":"Error","span":null,"visibility":"default","docs":null,"links":{},"attrs":[],"deprecation":null,"inner":{"assoc_type":{"generics":{"params":[],"where_predicates":[]},"bounds":[],"default":{"resolved_path":{"name":"Infallible","id":"1:32689:3734","args":{"angle_bracketed":{"args":[],"bindings":[]}}}}}}},"b:1:2787-0:14:1823":{"id":"b:1:2787-0:14:1823","crate_id":0,"name":null,"span":null,"visibility":"default","docs":null,"links":{},"attrs":[],"deprecation":null,"inner":{"impl":{"is_unsafe":false,"generics":{"params":[{"name":"T","kind":{"type":{"bounds":[],"default":null,"synthetic":false}}},{"name":"U","kind":{"type":{"bounds":[],"default":null,"synthetic":false}}}],"where_predicates":[{"bound_predicate":{"type":{"generic":"U"},"bounds":[{"trait_bound":{"trait":{"name":"Into","id":"1:2746:163","args":{"angle_bracketed":{"args":[{"type":{"generic":"T"}}],"bindings":[]}}},"generic_params":[],"modifier":"none"}}],"generic_params":[]}}]},"provided_trait_methods":[],"trait":{"name":"TryFrom","id":"1:2756:256","args":{"angle_bracketed":{"args":[{"type":{"generic":"U"}}],"bindings":[]}}},"for":{"resolved_path":{"name":"Buffer","id":"0:14:1823","args":{"angle_bracketed":{"args":[],"bindings":[]}}}},"items":["1:2790:138","1:2791:1629"],"negative":false,"synthetic":false,"blanket_impl":{"generic":"T"}}}},"1:3610:1644":{"id":"1:3610:1644","crate_id":1,"name":"type_id","span":null,"visibility":"default","docs":null,"links":{},"attrs":[],"deprecation":null,"inner":{"function":{"decl":{"inputs":[["self",{"borrowed_ref":{"lifetime":null,"mutable":false,"type":{"generic":"Self"}}}]],"output":{"resolved_path":{"name":"TypeId","id":"1:40059:3152","args":{"angle_bracketed":{"args":[],"bindings":[]}}}},"c_variadic":false},"generics":{"params":[],"where_predicates":[]},"header":{"const":false,"unsafe":false,"async":false,"abi":"Rust"},"has_body":true}}},"0:70":{"id":"0:70","crate_id":0,"name":null,"span":{"filename":"src/lib.rs","begin":[207,0],"end":[214,11]},"visibility":"default","docs":null,"links":{},"attrs":[],"deprecation":null,"inner":{"impl":{"is_unsafe":false,"generics":{"params":[],"where_predicates":[]},"provided_trait_methods":[],"trait":{"name":"Integer","id":"0:28:1833","args":{"angle_bracketed":{"args":[],"bindings":[]}}},"for":{"primitive":"i32"},"items":[],"negative":false,"synthetic":false,"blanket_impl":null}}},"0:17":{"id":"0:17","crate_id":0,"name":null,"span":{"filename":"src/lib.rs","begin":[65,0],"end":[70,1]},"visibility":"default","docs":null,"links":{},"attrs":[],"deprecation":null,"inner":{"impl":{"is_unsafe":false,"generics":{"params":[],"where_predicates":[]},"provided_trait_methods":[],"trait":{"name":"Default","id":"1:2824:126","args":{"angle_bracketed":{"args":[],"bindings":[]}}},"for":{"resolved_path":{"name":"Buffer","id":"0:14:1823","args":{"angle_bracketed":{"args":[],"bindings":[]}}}},"items":["0:18:60"],"negative":false,"synthetic":false,"blanket_impl":null}}},"0:88":{"id":"0:88","crate_id":0,"name":null,"span":{"filename":"src/lib.rs","begin":[216,0],"end":[216,60]},"visibility":"default","docs":null,"links":{},"attrs":[],"deprecation":null,"inner":{"impl":{"is_unsafe":false,"generics":{"params":[],"where_predicates":[]},"provided_trait_methods":[],"trait":{"name":"Integer","id":"0:28:1833","args":{"angle_bracketed":{"args":[],"bindings":[]}}},"for":{"primitive":"u64"},"items":[],"negative":false,"synthetic":false,"blanket_impl":null}}},"0:52":{"id":"0:52","crate_id":0,"name":null,"span":{"filename":"src/lib.rs","begin":[207,0],"end":[214,11]},"visibility":"default","docs":null,"links":{},"attrs":[],"deprecation":null,"inner":{"impl":{"is_unsafe":false,"generics":{"params":[],"where_predicates":[]},"provided_trait_methods":[],"trait":{"name":"Integer","id":"0:28:1833","args":{"angle_bracketed":{"args":[],"bindings":[]}}},"for":{"primitive":"u8"},"items":[],"negative":false,"synthetic":false,"blanket_impl":null}}},"a:1:42396:3885-0:14:1823":{"id":"a:1:42396:3885-0:14:1823","crate_id":0,"name":null,"span":null,"visibility":"default","docs":null,"links":{},"attrs":[],"deprecation":null,"inner":{"impl":{"is_unsafe":false,"generics":{"params":[],"where_predicates":[]},"provided_trait_methods":[],"trait":{"name":"UnwindSafe","id":"1:42396:3885","args":{"angle_bracketed":{"args":[],"bindings":[]}}},"for":{"resolved_path":{"name":"Buffer","id":"0:14:1823","args":{"angle_bracketed":{"args":[],"bindings":[]}}}},"items":[],"negative":false,"synthetic":true,"blanket_impl":null}}},"0:94":{"id":"0:94","crate_id":0,"name":null,"span":{"filename":"src/lib.rs","begin":[225,0],"end":[225,64]},"visibility":"default","docs":null,"links":{},"attrs":[],"deprecation":null,"inner":{"impl":{"is_unsafe":false,"generics":{"params":[],"where_predicates":[]},"provided_trait_methods":[],"trait":{"name":"Integer","id":"0:28:1833","args":{"angle_bracketed":{"args":[],"bindings":[]}}},"for":{"primitive":"isize"},"items":[],"negative":false,"synthetic":false,"blanket_impl":null}}},"1:2791:1629":{"id":"1:2791:1629","crate_id":1,"name":"try_from","span":null,"visibility":"default","docs":null,"links":{},"attrs":[],"deprecation":null,"inner":{"function":{"decl":{"inputs":[["value",{"generic":"U"}]],"output":{"resolved_path":{"name":"Result","id":"1:42415:226","args":{"angle_bracketed":{"args":[{"type":{"generic":"T"}},{"type":{"qualified_path":{"name":"Error","args":{"angle_bracketed":{"args":[],"bindings":[]}},"self_type":{"generic":"T"},"trait":{"name":"TryFrom","id":"1:2756:256","args":{"angle_bracketed":{"args":[{"type":{"generic":"U"}}],"bindings":[]}}}}}}],"bindings":[]}}}},"c_variadic":false},"generics":{"params":[],"where_predicates":[]},"header":{"const":false,"unsafe":false,"async":false,"abi":"Rust"},"has_body":true}}},"0:64":{"id":"0:64","crate_id":0,"name":null,"span":{"filename":"src/lib.rs","begin":[207,0],"end":[214,11]},"visibility":"default","docs":null,"links":{},"attrs":[],"deprecation":null,"inner":{"impl":{"is_unsafe":false,"generics":{"params":[],"where_predicates":[]},"provided_trait_methods":[],"trait":{"name":"Integer","id":"0:28:1833","args":{"angle_bracketed":{"args":[],"bindings":[]}}},"for":{"primitive":"u16"},"items":[],"negative":false,"synthetic":false,"blanket_impl":null}}},"0:76":{"id":"0:76","crate_id":0,"name":null,"span":{"filename":"src/lib.rs","begin":[207,0],"end":[214,11]},"visibility":"default","docs":null,"links":{},"attrs":[],"deprecation":null,"inner":{"impl":{"is_unsafe":false,"generics":{"params":[],"where_predicates":[]},"provided_trait_methods":[],"trait":{"name":"Integer","id":"0:28:1833","args":{"angle_bracketed":{"args":[],"bindings":[]}}},"for":{"primitive":"u32"},"items":[],"negative":false,"synthetic":false,"blanket_impl":null}}},"0:46":{"id":"0:46","crate_id":0,"name":null,"span":{"filename":"src/lib.rs","begin":[207,0],"end":[214,11]},"visibility":"default","docs":null,"links":{},"attrs":[],"deprecation":null,"inner":{"impl":{"is_unsafe":false,"generics":{"params":[],"where_predicates":[]},"provided_trait_methods":[],"trait":{"name":"Integer","id":"0:28:1833","args":{"angle_bracketed":{"args":[],"bindings":[]}}},"for":{"primitive":"i8"},"items":[],"negative":false,"synthetic":false,"blanket_impl":null}}},"0:114":{"id":"0:114","crate_id":0,"name":null,"span":{"filename":"src/lib.rs","begin":[295,0],"end":[295,60]},"visibility":"default","docs":null,"links":{},"attrs":[],"deprecation":null,"inner":{"impl":{"is_unsafe":false,"generics":{"params":[],"where_predicates":[]},"provided_trait_methods":[],"trait":{"name":"Integer","id":"0:28:1833","args":{"angle_bracketed":{"args":[],"bindings":[]}}},"for":{"primitive":"u128"},"items":[],"negative":false,"synthetic":false,"blanket_impl":null}}},"0:58":{"id":"0:58","crate_id":0,"name":null,"span":{"filename":"src/lib.rs","begin":[207,0],"end":[214,11]},"visibility":"default","docs":null,"links":{},"attrs":[],"deprecation":null,"inner":{"impl":{"is_unsafe":false,"generics":{"params":[],"where_predicates":[]},"provided_trait_methods":[],"trait":{"name":"Integer","id":"0:28:1833","args":{"angle_bracketed":{"args":[],"bindings":[]}}},"for":{"primitive":"i16"},"items":[],"negative":false,"synthetic":false,"blanket_impl":null}}},"0:25:736":{"id":"0:25:736","crate_id":0,"name":"format","span":{"filename":"src/lib.rs","begin":[95,4],"end":[100,5]},"visibility":"public","docs":"Print an integer into this buffer and return a reference to its string\nrepresentation within the buffer.","links":{},"attrs":[],"deprecation":null,"inner":{"function":{"decl":{"inputs":[["self",{"borrowed_ref":{"lifetime":null,"mutable":true,"type":{"generic":"Self"}}}],["i",{"generic":"I"}]],"output":{"borrowed_ref":{"lifetime":null,"mutable":false,"type":{"primitive":"str"}}},"c_variadic":false},"generics":{"params":[{"name":"I","kind":{"type":{"bounds":[{"trait_bound":{"trait":{"name":"Integer","id":"0:28:1833","args":{"angle_bracketed":{"args":[],"bindings":[]}}},"generic_params":[],"modifier":"none"}}],"default":null,"synthetic":false}}}],"where_predicates":[]},"header":{"const":false,"unsafe":false,"async":false,"abi":"Rust"},"has_body":true}}},"0:21:458":{"id":"0:21:458","crate_id":0,"name":"clone","span":{"filename":"src/lib.rs","begin":[77,4],"end":[79,5]},"visibility":"default","docs":null,"links":{},"attrs":["#[inline]","#[allow(clippy::non_canonical_clone_impl)]"],"deprecation":null,"inner":{"function":{"decl":{"inputs":[["self",{"borrowed_ref":{"lifetime":null,"mutable":false,"type":{"generic":"Self"}}}]],"output":{"generic":"Self"},"c_variadic":false},"generics":{"params":[],"where_predicates":[]},"header":{"const":false,"unsafe":false,"async":false,"abi":"Rust"},"has_body":true}}},"0:14:1823":{"id":"0:14:1823","crate_id":0,"name":"Buffer","span":{"filename":"src/lib.rs","begin":[61,0],"end":[63,1]},"visibility":"public","docs":"A correctly sized stack allocation for the formatted integer to be written\ninto.\n\n# Example\n\n```\nlet mut buffer = itoa::Buffer::new();\nlet printed = buffer.format(1234);\nassert_eq!(printed, \"1234\");\n```","links":{},"attrs":[],"deprecation":null,"inner":{"struct":{"kind":{"plain":{"fields":[],"fields_stripped":true}},"generics":{"params":[],"where_predicates":[]},"impls":["0:22","a:1:42397:3884-0:14:1823","a:1:2995:246-0:14:1823","a:1:32761:237-0:14:1823","a:1:42396:3885-0:14:1823","a:1:32818:2141-0:14:1823","b:1:2772-0:14:1823","b:1:2782-0:14:1823","b:1:2787-0:14:1823","b:1:2776-0:14:1823","b:1:2472-0:14:1823","b:1:3608-0:14:1823","b:1:2469-0:14:1823","0:17","0:19","0:20"]}}},"0:31:1823":{"id":"0:31:1823","crate_id":0,"name":"Buffer","span":{"filename":"src/lib.rs","begin":[111,8],"end":[111,29]},"visibility":"default","docs":null,"links":{},"attrs":[],"deprecation":null,"inner":{"assoc_type":{"generics":{"params":[],"where_predicates":[]},"bounds":[{"outlives":"'static"}],"default":null}}},"0:19":{"id":"0:19","crate_id":0,"name":null,"span":{"filename":"src/lib.rs","begin":[72,0],"end":[72,23]},"visibility":"default","docs":null,"links":{},"attrs":[],"deprecation":null,"inner":{"impl":{"is_unsafe":false,"generics":{"params":[],"where_predicates":[]},"provided_trait_methods":[],"trait":{"name":"Copy","id":"1:2990:119","args":{"angle_bracketed":{"args":[],"bindings":[]}}},"for":{"resolved_path":{"name":"Buffer","id":"0:14:1823","args":{"angle_bracketed":{"args":[],"bindings":[]}}}},"items":[],"negative":false,"synthetic":false,"blanket_impl":null}}},"0:82":{"id":"0:82","crate_id":0,"name":null,"span":{"filename":"src/lib.rs","begin":[216,0],"end":[216,60]},"visibility":"default","docs":null,"links":{},"attrs":[],"deprecation":null,"inner":{"impl":{"is_unsafe":false,"generics":{"params":[],"where_predicates":[]},"provided_trait_methods":[],"trait":{"name":"Integer","id":"0:28:1833","args":{"angle_bracketed":{"args":[],"bindings":[]}}},"for":{"primitive":"i64"},"items":[],"negative":false,"synthetic":false,"blanket_impl":null}}},"b:1:3608-0:14:1823":{"id":"b:1:3608-0:14:1823","crate_id":0,"name":null,"span":null,"visibility":"default","docs":null,"links":{},"attrs":[],"deprecation":null,"inner":{"impl":{"is_unsafe":false,"generics":{"params":[{"name":"T","kind":{"type":{"bounds":[],"default":null,"synthetic":false}}}],"where_predicates":[{"bound_predicate":{"type":{"generic":"T"},"bounds":[{"outlives":"'static"},{"trait_bound":{"trait":{"name":"Sized","id":"1:32762:2140","args":{"angle_bracketed":{"args":[],"bindings":[]}}},"generic_params":[],"modifier":"maybe"}}],"generic_params":[]}}]},"provided_trait_methods":[],"trait":{"name":"Any","id":"1:3606:71","args":{"angle_bracketed":{"args":[],"bindings":[]}}},"for":{"resolved_path":{"name":"Buffer","id":"0:14:1823","args":{"angle_bracketed":{"args":[],"bindings":[]}}}},"items":["1:3610:1644"],"negative":false,"synthetic":false,"blanket_impl":{"generic":"T"}}}},"1:2474:9265":{"id":"1:2474:9265","crate_id":1,"name":"borrow_mut","span":null,"visibility":"default","docs":null,"links":{},"attrs":[],"deprecation":null,"inner":{"function":{"decl":{"inputs":[["self",{"borrowed_ref":{"lifetime":null,"mutable":true,"type":{"generic":"Self"}}}]],"output":{"borrowed_ref":{"lifetime":null,"mutable":true,"type":{"generic":"T"}}},"c_variadic":false},"generics":{"params":[],"where_predicates":[]},"header":{"const":false,"unsafe":false,"async":false,"abi":"Rust"},"has_body":true}}},"0:23:1048":{"id":"0:23:1048","crate_id":0,"name":"new","span":{"filename":"src/lib.rs","begin":[87,4],"end":[90,5]},"visibility":"public","docs":"This is a cheap operation; you don't need to worry about reusing buffers\nfor efficiency.","links":{},"attrs":["#[inline]"],"deprecation":null,"inner":{"function":{"decl":{"inputs":[],"output":{"resolved_path":{"name":"Buffer","id":"0:14:1823","args":{"angle_bracketed":{"args":[],"bindings":[]}}}},"c_variadic":false},"generics":{"params":[],"where_predicates":[]},"header":{"const":false,"unsafe":false,"async":false,"abi":"Rust"},"has_body":true}}},"0:28:1833":{"id":"0:28:1833","crate_id":0,"name":"Integer","span":{"filename":"src/lib.rs","begin":[106,0],"end":[106,37]},"visibility":"public","docs":"An integer that can be written into an [`itoa::Buffer`][Buffer].\n\nThis trait is sealed and cannot be implemented for types outside of itoa.","links":{"Buffer":"0:14:1823"},"attrs":[],"deprecation":null,"inner":{"trait":{"is_auto":false,"is_unsafe":false,"is_object_safe":false,"items":[],"generics":{"params":[],"where_predicates":[]},"bounds":[{"trait_bound":{"trait":{"name":"private::Sealed","id":"0:30:1836","args":{"angle_bracketed":{"args":[],"bindings":[]}}},"generic_params":[],"modifier":"none"}}],"implementations":["0:88","0:70","0:52","0:94","0:100","0:106","0:64","0:76","0:46","0:114","0:58","0:82"]}}},"1:2471:2022":{"id":"1:2471:2022","crate_id":1,"name":"borrow","span":null,"visibility":"default","docs":null,"links":{},"attrs":["#[rustc_diagnostic_item = \"noop_method_borrow\"]"],"deprecation":null,"inner":{"function":{"decl":{"inputs":[["self",{"borrowed_ref":{"lifetime":null,"mutable":false,"type":{"generic":"Self"}}}]],"output":{"borrowed_ref":{"lifetime":null,"mutable":false,"type":{"generic":"T"}}},"c_variadic":false},"generics":{"params":[],"where_predicates":[]},"header":{"const":false,"unsafe":false,"async":false,"abi":"Rust"},"has_body":true}}},"a:1:42397:3884-0:14:1823":{"id":"a:1:42397:3884-0:14:1823","crate_id":0,"name":null,"span":null,"visibility":"default","docs":null,"links":{},"attrs":[],"deprecation":null,"inner":{"impl":{"is_unsafe":false,"generics":{"params":[],"where_predicates":[]},"provided_trait_methods":[],"trait":{"name":"RefUnwindSafe","id":"1:42397:3884","args":{"angle_bracketed":{"args":[],"bindings":[]}}},"for":{"resolved_path":{"name":"Buffer","id":"0:14:1823","args":{"angle_bracketed":{"args":[],"bindings":[]}}}},"items":[],"negative":false,"synthetic":true,"blanket_impl":null}}},"a:1:2995:246-0:14:1823":{"id":"a:1:2995:246-0:14:1823","crate_id":0,"name":null,"span":null,"visibility":"default","docs":null,"links":{},"attrs":[],"deprecation":null,"inner":{"impl":{"is_unsafe":false,"generics":{"params":[],"where_predicates":[]},"provided_trait_methods":[],"trait":{"name":"Sync","id":"1:2995:246","args":{"angle_bracketed":{"args":[],"bindings":[]}}},"for":{"resolved_path":{"name":"Buffer","id":"0:14:1823","args":{"angle_bracketed":{"args":[],"bindings":[]}}}},"items":[],"negative":false,"synthetic":true,"blanket_impl":null}}},"0:32:1834":{"id":"0:32:1834","crate_id":0,"name":"write","span":{"filename":"src/lib.rs","begin":[112,8],"end":[112,55]},"visibility":"default","docs":null,"links":{},"attrs":[],"deprecation":null,"inner":{"function":{"decl":{"inputs":[["self",{"generic":"Self"}],["buf",{"borrowed_ref":{"lifetime":null,"mutable":true,"type":{"qualified_path":{"name":"Buffer","args":{"angle_bracketed":{"args":[],"bindings":[]}},"self_type":{"generic":"Self"},"trait":{"name":"","id":"0:30:1836","args":null}}}}}]],"output":{"borrowed_ref":{"lifetime":null,"mutable":false,"type":{"primitive":"str"}}},"c_variadic":false},"generics":{"params":[],"where_predicates":[]},"header":{"const":false,"unsafe":false,"async":false,"abi":"Rust"},"has_body":false}}},"a:1:32818:2141-0:14:1823":{"id":"a:1:32818:2141-0:14:1823","crate_id":0,"name":null,"span":null,"visibility":"default","docs":null,"links":{},"attrs":[],"deprecation":null,"inner":{"impl":{"is_unsafe":false,"generics":{"params":[],"where_predicates":[]},"provided_trait_methods":[],"trait":{"name":"Unpin","id":"1:32818:2141","args":{"angle_bracketed":{"args":[],"bindings":[]}}},"for":{"resolved_path":{"name":"Buffer","id":"0:14:1823","args":{"angle_bracketed":{"args":[],"bindings":[]}}}},"items":[],"negative":false,"synthetic":true,"blanket_impl":null}}},"b:1:2782-0:14:1823":{"id":"b:1:2782-0:14:1823","crate_id":0,"name":null,"span":null,"visibility":"default","docs":null,"links":{},"attrs":[],"deprecation":null,"inner":{"impl":{"is_unsafe":false,"generics":{"params":[{"name":"T","kind":{"type":{"bounds":[],"default":null,"synthetic":false}}},{"name":"U","kind":{"type":{"bounds":[],"default":null,"synthetic":false}}}],"where_predicates":[{"bound_predicate":{"type":{"generic":"U"},"bounds":[{"trait_bound":{"trait":{"name":"TryFrom","id":"1:2756:256","args":{"angle_bracketed":{"args":[{"type":{"generic":"T"}}],"bindings":[]}}},"generic_params":[],"modifier":"none"}}],"generic_params":[]}}]},"provided_trait_methods":[],"trait":{"name":"TryInto","id":"1:2752:257","args":{"angle_bracketed":{"args":[{"type":{"generic":"U"}}],"bindings":[]}}},"for":{"resolved_path":{"name":"Buffer","id":"0:14:1823","args":{"angle_bracketed":{"args":[],"bindings":[]}}}},"items":["1:2785:138","1:2786:1631"],"negative":false,"synthetic":false,"blanket_impl":{"generic":"T"}}}}},"paths":{"1:34736:3765":{"crate_id":1,"path":["core","ops","bit","Shl"],"kind":"trait"},"1:41285:3451":{"crate_id":1,"path":["core","iter","adapters","zip","Zip"],"kind":"struct"},"1:2485:114":{"crate_id":1,"path":["core","clone","Clone"],"kind":"trait"},"1:48570:3315":{"crate_id":1,"path":["core","core_arch","x86","cpuid","CpuidResult"],"kind":"struct"},"1:4232:11855":{"crate_id":1,"path":["core","asserting","TryCaptureWithDebug"],"kind":"struct"},"1:32738:12342":{"crate_id":1,"path":["core","error","tags","MaybeSizedValue"],"kind":"struct"},"1:31508:196":{"crate_id":1,"path":["core","cmp","Ordering"],"kind":"enum"},"1:9706:12247":{"crate_id":1,"path":["core","fmt","builders","PadAdapter"],"kind":"struct"},"1:22835:3065":{"crate_id":1,"path":["core","num","diy_float","Fp"],"kind":"struct"},"1:46121:3212":{"crate_id":1,"path":["core","core_arch","simd","u16x2"],"kind":"struct"},"1:21400:12347":{"crate_id":1,"path":["core","core_simd","swizzle","rotate_elements_left","Rotate"],"kind":"struct"},"1:22650:3395":{"crate_id":1,"path":["core","num","bignum","Big32x40"],"kind":"struct"},"1:46407:3224":{"crate_id":1,"path":["core","core_arch","simd","f64x1"],"kind":"struct"},"1:38598:3769":{"crate_id":1,"path":["core","ops","bit","BitXorAssign"],"kind":"trait"},"1:22565:9085":{"crate_id":1,"path":["core","core_simd","simd","cmp","ord","SimdPartialOrd"],"kind":"trait"},"1:44602:3487":{"crate_id":1,"path":["core","str","pattern","CharArrayRefSearcher"],"kind":"struct"},"1:47124:3259":{"crate_id":1,"path":["core","core_arch","simd","u32x8"],"kind":"struct"},"1:7385:3873":{"crate_id":1,"path":["core","iter","adapters","zip","TrustedRandomAccessNoCoerce"],"kind":"trait"},"1:10977:2399":{"crate_id":1,"path":["core","slice","iter","SplitMut"],"kind":"struct"},"1:43315:138":{"crate_id":1,"path":["core","fmt","Error"],"kind":"struct"},"1:4626:3811":{"crate_id":1,"path":["core","cell","BorrowRefMut"],"kind":"struct"},"1:10052:130":{"crate_id":1,"path":["core","fmt","Display"],"kind":"trait"},"1:7952:146":{"crate_id":1,"path":["core","iter","traits","collect","FromIterator"],"kind":"trait"},"1:46600:3233":{"crate_id":1,"path":["core","core_arch","simd","i8x16"],"kind":"struct"},"1:34217:3761":{"crate_id":1,"path":["core","ops","bit","BitAnd"],"kind":"trait"},"1:53608:333":{"crate_id":1,"path":["core","array"],"kind":"primitive"},"1:43543:2956":{"crate_id":1,"path":["core","hash","sip","Sip13Rounds"],"kind":"struct"},"1:44125:2500":{"crate_id":1,"path":["core","str","iter","Chars"],"kind":"struct"},"1:41478:3454":{"crate_id":1,"path":["core","iter","sources","from_fn","FromFn"],"kind":"struct"},"1:0:537":{"crate_id":1,"path":["core"],"kind":"module"},"1:32727:9740":{"crate_id":1,"path":["core","error","private","Internal"],"kind":"struct"},"1:41271:3450":{"crate_id":1,"path":["core","iter","adapters","take_while","TakeWhile"],"kind":"struct"},"1:44277:2396":{"crate_id":1,"path":["core","str","iter","RSplitN"],"kind":"struct"},"1:39811:2208":{"crate_id":1,"path":["core","ops","control_flow","ControlFlow"],"kind":"enum"},"1:43496:2952":{"crate_id":1,"path":["core","hash","sip","SipHasher13"],"kind":"struct"},"1:44438:2514":{"crate_id":1,"path":["core","str","iter","SplitAsciiWhitespace"],"kind":"struct"},"1:43521:157":{"crate_id":1,"path":["core","hash","sip","Hasher"],"kind":"struct"},"1:33610:3755":{"crate_id":1,"path":["core","ops","arith","Rem"],"kind":"trait"},"1:2703:1836":{"crate_id":1,"path":["core","convert","num","private","Sealed"],"kind":"trait"},"1:44131:2499":{"crate_id":1,"path":["core","str","iter","CharIndices"],"kind":"struct"},"1:40713:3413":{"crate_id":1,"path":["core","char","decode","DecodeUtf16"],"kind":"struct"},"1:12573:2497":{"crate_id":1,"path":["core","str","traits","FromStr"],"kind":"trait"},"1:10271:157":{"crate_id":1,"path":["core","hash","Hasher"],"kind":"trait"},"1:42699:95":{"crate_id":1,"path":["core","sync","atomic","AtomicU32"],"kind":"struct"},"1:40913:2410":{"crate_id":1,"path":["core","iter","adapters","array_chunks","ArrayChunks"],"kind":"struct"},"1:9851:2183":{"crate_id":1,"path":["core","fmt","builders","FormatterFn"],"kind":"struct"},"1:40876:3372":{"crate_id":1,"path":["core","ffi","VaListImpl"],"kind":"struct"},"1:5018:422":{"crate_id":1,"path":["core","ffi","c_void"],"kind":"enum"},"1:2381:2296":{"crate_id":1,"path":["core","ptr","from_exposed_addr_mut"],"kind":"function"},"3:0:2088":{"crate_id":3,"path":["rustc_std_workspace_core"],"kind":"module"},"1:30965:1815":{"crate_id":1,"path":["core","mem","maybe_uninit","MaybeUninit"],"kind":"union"},"1:45164:3509":{"crate_id":1,"path":["core","alloc","layout","LayoutError"],"kind":"struct"},"1:44004:2412":{"crate_id":1,"path":["core","slice","iter","ArrayWindows"],"kind":"struct"},"1:45077:227":{"crate_id":1,"path":["core","future","ResumeTy"],"kind":"struct"},"1:46676:3235":{"crate_id":1,"path":["core","core_arch","simd","i32x4"],"kind":"struct"},"1:42012:171":{"crate_id":1,"path":["core","net","ip_addr","IpAddr"],"kind":"enum"},"1:39907:213":{"crate_id":1,"path":["core","ops","range","RangeFull"],"kind":"struct"},"1:10870:2203":{"crate_id":1,"path":["core","slice","iter","IterMut"],"kind":"struct"},"1:40776:3418":{"crate_id":1,"path":["core","char","ToUppercase"],"kind":"struct"},"1:5828:3792":{"crate_id":1,"path":["core","iter","adapters","filter_map","next_chunk","Guard"],"kind":"struct"},"1:42463:2203":{"crate_id":1,"path":["core","result","IterMut"],"kind":"struct"},"1:46500:3230":{"crate_id":1,"path":["core","core_arch","simd","u16x8"],"kind":"struct"},"1:46099:3211":{"crate_id":1,"path":["core","core_arch","simd","u8x4"],"kind":"struct"},"1:10022:144":{"crate_id":1,"path":["core","fmt","Formatter"],"kind":"struct"},"1:42330:2202":{"crate_id":1,"path":["core","option","Iter"],"kind":"struct"},"1:44677:3490":{"crate_id":1,"path":["core","str","pattern","CharPredicateSearcher"],"kind":"struct"},"1:47390:3264":{"crate_id":1,"path":["core","core_arch","simd","i64x4"],"kind":"struct"},"1:2537:135":{"crate_id":1,"path":["core","cmp","Eq"],"kind":"trait"},"1:45085:207":{"crate_id":1,"path":["core","task","poll","Poll"],"kind":"enum"},"1:40072:3153":{"crate_id":1,"path":["core","array","TryFromSliceError"],"kind":"struct"},"0:0:1880":{"crate_id":0,"path":["itoa"],"kind":"module"},"1:40245:3735":{"crate_id":1,"path":["core","ascii","ascii_char","AsciiChar"],"kind":"enum"},"1:44780:2491":{"crate_id":1,"path":["core","str","lossy","Utf8Chunks"],"kind":"struct"},"1:11143:2396":{"crate_id":1,"path":["core","slice","iter","RSplitN"],"kind":"struct"},"1:30709:3529":{"crate_id":1,"path":["core","num","FpCategory"],"kind":"enum"},"1:48508:3313":{"crate_id":1,"path":["core","core_arch","x86","__m256bh"],"kind":"struct"},"1:42660:88":{"crate_id":1,"path":["core","sync","atomic","AtomicI32"],"kind":"struct"},"1:42398:2134":{"crate_id":1,"path":["core","panicking","AssertKind"],"kind":"enum"},"1:44141:2498":{"crate_id":1,"path":["core","str","iter","Bytes"],"kind":"struct"},"1:42738:89":{"crate_id":1,"path":["core","sync","atomic","AtomicI64"],"kind":"struct"},"1:13444:3392":{"crate_id":1,"path":["core","task","wake","Waker"],"kind":"struct"},"1:42407:2207":{"crate_id":1,"path":["core","pin","Pin"],"kind":"struct"},"1:4507:3804":{"crate_id":1,"path":["core","cell","BorrowMutError"],"kind":"struct"},"1:44223:2504":{"crate_id":1,"path":["core","str","iter","RSplitTerminator"],"kind":"struct"},"1:44472:2513":{"crate_id":1,"path":["core","str","iter","EscapeUnicode"],"kind":"struct"},"1:4286:3800":{"crate_id":1,"path":["core","async_iter","async_iter","IntoAsyncIterator"],"kind":"trait"},"1:2017:189":{"crate_id":1,"path":["core","ptr","non_null","NonNull"],"kind":"struct"},"1:31159:10055":{"crate_id":1,"path":["core","ptr","alignment","AlignmentEnum64"],"kind":"enum"},"1:44454:2511":{"crate_id":1,"path":["core","str","iter","EscapeDebug"],"kind":"struct"},"1:44903:2811":{"crate_id":1,"path":["core","time","Nanoseconds"],"kind":"struct"},"1:44419:2503":{"crate_id":1,"path":["core","str","iter","LinesAny"],"kind":"struct"},"1:22941:3403":{"crate_id":1,"path":["core","num","error","ParseIntError"],"kind":"struct"},"1:43755:2421":{"crate_id":1,"path":["core","slice","ascii","EscapeAscii"],"kind":"struct"},"1:22536:9084":{"crate_id":1,"path":["core","core_simd","simd","cmp","eq","SimdPartialEq"],"kind":"trait"},"1:40993:3429":{"crate_id":1,"path":["core","iter","adapters","filter","Filter"],"kind":"struct"},"1:46744:3238":{"crate_id":1,"path":["core","core_arch","simd","f64x2"],"kind":"struct"},"1:10004:2158":{"crate_id":1,"path":["core","fmt","Write"],"kind":"trait"},"1:48356:3302":{"crate_id":1,"path":["core","core_arch","simd","f64x8"],"kind":"struct"},"1:45187:3510":{"crate_id":1,"path":["core","escape","EscapeIterInner"],"kind":"struct"},"1:41261:3449":{"crate_id":1,"path":["core","iter","adapters","take","Take"],"kind":"struct"},"1:30986:2169":{"crate_id":1,"path":["core","ptr","alignment","Alignment"],"kind":"struct"},"1:41055:3437":{"crate_id":1,"path":["core","iter","adapters","map","Map"],"kind":"struct"},"1:48234:3299":{"crate_id":1,"path":["core","core_arch","simd","f32x16"],"kind":"struct"},"1:43015:2162":{"crate_id":1,"path":["core","fmt","num","UpperHex"],"kind":"struct"},"1:48394:3305":{"crate_id":1,"path":["core","core_arch","x86","__m128d"],"kind":"struct"},"1:3441:147":{"crate_id":1,"path":["core","ops","try_trait","FromResidual"],"kind":"trait"},"1:7449:11561":{"crate_id":1,"path":["core","iter","adapters","GenericShunt"],"kind":"struct"},"1:11157:2401":{"crate_id":1,"path":["core","slice","iter","SplitNMut"],"kind":"struct"},"1:7501:3857":{"crate_id":1,"path":["core","iter","range","Step"],"kind":"trait"},"1:2756:256":{"crate_id":1,"path":["core","convert","TryFrom"],"kind":"trait"},"1:47922:3295":{"crate_id":1,"path":["core","core_arch","simd","i16x32"],"kind":"struct"},"1:22810:3398":{"crate_id":1,"path":["core","num","dec2flt","ParseFloatError"],"kind":"struct"},"1:41034:3435":{"crate_id":1,"path":["core","iter","adapters","inspect","Inspect"],"kind":"struct"},"1:22490:2295":{"crate_id":1,"path":["core","core_simd","simd","ptr","mut_ptr","SimdMutPtr","from_exposed_addr"],"kind":"function"},"1:10417:3918":{"crate_id":1,"path":["core","slice","sort","InsertionHole"],"kind":"struct"},"1:43964:2393":{"crate_id":1,"path":["core","slice","iter","Chunks"],"kind":"struct"},"1:1939:3060":{"crate_id":1,"path":["core","ptr","metadata","PtrComponents"],"kind":"struct"},"1:46698:3236":{"crate_id":1,"path":["core","core_arch","simd","i64x2"],"kind":"struct"},"1:44043:2411":{"crate_id":1,"path":["core","slice","iter","ArrayChunksMut"],"kind":"struct"},"1:12684:3935":{"crate_id":1,"path":["core","str","pattern","MultiCharEqPattern"],"kind":"struct"},"1:44065:2409":{"crate_id":1,"path":["core","slice","iter","RChunksMut"],"kind":"struct"},"1:44571:3483":{"crate_id":1,"path":["core","str","pattern","MultiCharEqSearcher"],"kind":"struct"},"1:44895:2478":{"crate_id":1,"path":["core","str","BytesIsNotEmpty"],"kind":"struct"},"1:39982:214":{"crate_id":1,"path":["core","ops","range","RangeInclusive"],"kind":"struct"},"1:21429:12354":{"crate_id":1,"path":["core","core_simd","swizzle","interleave","Hi"],"kind":"struct"},"1:53620:800":{"crate_id":1,"path":["core","i128"],"kind":"primitive"},"1:40769:3417":{"crate_id":1,"path":["core","char","ToLowercase"],"kind":"struct"},"1:48374:3303":{"crate_id":1,"path":["core","core_arch","x86","__m128i"],"kind":"struct"},"1:5904:3378":{"crate_id":1,"path":["core","iter","adapters","flatten","FlatMap"],"kind":"struct"},"1:53611:1634":{"crate_id":1,"path":["core","tuple"],"kind":"primitive"},"1:2704:3528":{"crate_id":1,"path":["core","convert","num","FloatToInt"],"kind":"trait"},"1:31054:10057":{"crate_id":1,"path":["core","ptr","alignment","AlignmentEnum32"],"kind":"enum"},"1:12391:2519":{"crate_id":1,"path":["core","str","iter","MatchesInternal"],"kind":"struct"},"1:3235:141":{"crate_id":1,"path":["core","ops","function","Fn"],"kind":"trait"},"1:43008:2161":{"crate_id":1,"path":["core","fmt","num","LowerHex"],"kind":"struct"},"1:3481:3783":{"crate_id":1,"path":["core","ops","unsize","CoerceUnsized"],"kind":"trait"},"1:13464:3394":{"crate_id":1,"path":["core","task","wake","LocalWaker"],"kind":"struct"},"1:46552:3232":{"crate_id":1,"path":["core","core_arch","simd","u64x2"],"kind":"struct"},"1:2743:77":{"crate_id":1,"path":["core","convert","AsMut"],"kind":"trait"},"1:10311:2809":{"crate_id":1,"path":["core","hash","BuildHasherDefault"],"kind":"struct"},"1:53623:1651":{"crate_id":1,"path":["core","u32"],"kind":"primitive"},"1:44323:2509":{"crate_id":1,"path":["core","str","iter","RMatchIndices"],"kind":"struct"},"1:12638:2487":{"crate_id":1,"path":["core","str","pattern","DoubleEndedSearcher"],"kind":"trait"},"1:7671:2796":{"crate_id":1,"path":["core","iter","sources","empty","Empty"],"kind":"struct"},"1:30971:2108":{"crate_id":1,"path":["core","mem","transmutability","Assume"],"kind":"struct"},"1:45139:3976":{"crate_id":1,"path":["core","task","wake","ContextBuilder"],"kind":"struct"},"1:6636:3386":{"crate_id":1,"path":["core","iter","adapters","map_windows","MapWindows"],"kind":"struct"},"1:21412:12347":{"crate_id":1,"path":["core","core_simd","swizzle","rotate_elements_right","Rotate"],"kind":"struct"},"1:53624:1652":{"crate_id":1,"path":["core","u64"],"kind":"primitive"},"1:3068:3772":{"crate_id":1,"path":["core","ops","async_function","AsyncFn"],"kind":"trait"},"1:8421:3867":{"crate_id":1,"path":["core","iter","traits","marker","TrustedStep"],"kind":"trait"},"1:3436:253":{"crate_id":1,"path":["core","ops","try_trait","Try"],"kind":"trait"},"1:42396:3885":{"crate_id":1,"path":["core","panic","unwind_safe","UnwindSafe"],"kind":"trait"},"1:13302:3975":{"crate_id":1,"path":["core","future","poll_fn","PollFn"],"kind":"struct"},"1:726:3570":{"crate_id":1,"path":["core","num","nonzero","ZeroablePrimitive"],"kind":"trait"},"1:41025:2794":{"crate_id":1,"path":["core","iter","adapters","fuse","Fuse"],"kind":"struct"},"1:43983:2404":{"crate_id":1,"path":["core","slice","iter","ChunksExact"],"kind":"struct"},"1:10062:206":{"crate_id":1,"path":["core","fmt","Pointer"],"kind":"trait"},"1:4244:111":{"crate_id":1,"path":["core","asserting","Capture"],"kind":"struct"},"1:11689:2414":{"crate_id":1,"path":["core","slice","iter","ChunkByMut"],"kind":"struct"},"1:22422:9092":{"crate_id":1,"path":["core","core_simd","simd","ptr","const_ptr","SimdConstPtr"],"kind":"trait"},"1:21602:9006":{"crate_id":1,"path":["core","core_simd","cast","SimdCast"],"kind":"trait"},"1:43955:2395":{"crate_id":1,"path":["core","slice","iter","Windows"],"kind":"struct"},"1:46145:3213":{"crate_id":1,"path":["core","core_arch","simd","i8x4"],"kind":"struct"},"1:5118:862":{"crate_id":1,"path":["core","iter"],"kind":"module"},"1:22843:3066":{"crate_id":1,"path":["core","num","flt2dec","decoder","Decoded"],"kind":"struct"},"1:8412:2205":{"crate_id":1,"path":["core","iter","traits","marker","FusedIterator"],"kind":"trait"},"1:10500:12064":{"crate_id":1,"path":["core","slice","sort","merge_sort","BufGuard"],"kind":"struct"},"1:1816:640":{"crate_id":1,"path":["core","mem","drop"],"kind":"function"},"1:2466:104":{"crate_id":1,"path":["core","borrow","BorrowMut"],"kind":"trait"},"1:40964:2791":{"crate_id":1,"path":["core","iter","adapters","copied","Copied"],"kind":"struct"},"1:44883:2485":{"crate_id":1,"path":["core","str","IsWhitespace"],"kind":"struct"},"1:42582:87":{"crate_id":1,"path":["core","sync","atomic","AtomicI16"],"kind":"struct"},"1:12152:1549":{"crate_id":1,"path":["core","str"],"kind":"module"},"1:48414:3307":{"crate_id":1,"path":["core","core_arch","x86","__m256"],"kind":"struct"},"1:53615:700":{"crate_id":1,"path":["core","f64"],"kind":"primitive"},"1:32848:3690":{"crate_id":1,"path":["core","marker","Tuple"],"kind":"trait"},"1:43336:2170":{"crate_id":1,"path":["core","fmt","Arguments"],"kind":"struct"},"1:3078:3774":{"crate_id":1,"path":["core","ops","async_function","AsyncFnOnce"],"kind":"trait"},"1:42252:3176":{"crate_id":1,"path":["core","net","socket_addr","SocketAddrV6"],"kind":"struct"},"1:22952:3583":{"crate_id":1,"path":["core","num","error","IntErrorKind"],"kind":"enum"},"1:44085:2408":{"crate_id":1,"path":["core","slice","iter","RChunksExactMut"],"kind":"struct"},"1:40663:3411":{"crate_id":1,"path":["core","async_iter","from_iter","FromIter"],"kind":"struct"},"1:43751:3470":{"crate_id":1,"path":["core","slice","ascii","EscapeByte"],"kind":"struct"},"1:21444:12359":{"crate_id":1,"path":["core","core_simd","swizzle","deinterleave","Even"],"kind":"struct"},"1:44867:2477":{"crate_id":1,"path":["core","str","LinesMap"],"kind":"struct"},"1:2369:641":{"crate_id":1,"path":["core","ptr","drop_in_place"],"kind":"function"},"1:4502:3803":{"crate_id":1,"path":["core","cell","BorrowError"],"kind":"struct"},"1:11171:2397":{"crate_id":1,"path":["core","slice","iter","RSplitNMut"],"kind":"struct"},"1:38653:3770":{"crate_id":1,"path":["core","ops","bit","ShlAssign"],"kind":"trait"},"1:40723:3414":{"crate_id":1,"path":["core","char","decode","DecodeUtf16Error"],"kind":"struct"},"1:32763:244":{"crate_id":1,"path":["core","marker","StructuralPartialEq"],"kind":"trait"},"1:41112:3443":{"crate_id":1,"path":["core","iter","adapters","skip","Skip"],"kind":"struct"},"1:53605:1669":{"crate_id":1,"path":["core","unit"],"kind":"primitive"},"1:40685:10064":{"crate_id":1,"path":["core","char","convert","CharErrorKind"],"kind":"enum"},"1:40846:3425":{"crate_id":1,"path":["core","ffi","c_str","FromBytesUntilNulError"],"kind":"struct"},"1:6647:1823":{"crate_id":1,"path":["core","iter","adapters","map_windows","Buffer"],"kind":"struct"},"1:3241:143":{"crate_id":1,"path":["core","ops","function","FnOnce"],"kind":"trait"},"1:21390:2819":{"crate_id":1,"path":["core","core_simd","swizzle","reverse","Reverse"],"kind":"struct"},"1:3207:127":{"crate_id":1,"path":["core","ops","deref","Deref"],"kind":"trait"},"1:42346:2204":{"crate_id":1,"path":["core","option","IntoIter"],"kind":"struct"},"1:2532:201":{"crate_id":1,"path":["core","cmp","PartialEq"],"kind":"trait"},"1:21427:12349":{"crate_id":1,"path":["core","core_simd","swizzle","interleave","Lo"],"kind":"struct"},"1:7994:131":{"crate_id":1,"path":["core","iter","traits","double_ended","DoubleEndedIterator"],"kind":"trait"},"1:47236:3261":{"crate_id":1,"path":["core","core_arch","simd","i8x32"],"kind":"struct"},"1:48429:3308":{"crate_id":1,"path":["core","core_arch","x86","__m256d"],"kind":"struct"},"1:38488:3767":{"crate_id":1,"path":["core","ops","bit","BitAndAssign"],"kind":"trait"},"1:44728:3942":{"crate_id":1,"path":["core","str","pattern","StrSearcherImpl"],"kind":"enum"},"1:22476:9093":{"crate_id":1,"path":["core","core_simd","simd","ptr","mut_ptr","SimdMutPtr"],"kind":"trait"},"1:48493:3312":{"crate_id":1,"path":["core","core_arch","x86","__m128bh"],"kind":"struct"},"1:33962:3758":{"crate_id":1,"path":["core","ops","arith","MulAssign"],"kind":"trait"},"1:39962:215":{"crate_id":1,"path":["core","ops","range","RangeTo"],"kind":"struct"},"1:42212:3880":{"crate_id":1,"path":["core","net","socket_addr","SocketAddr"],"kind":"enum"},"1:3606:71":{"crate_id":1,"path":["core","any","Any"],"kind":"trait"},"1:48110:3297":{"crate_id":1,"path":["core","core_arch","simd","i32x16"],"kind":"struct"},"1:728:190":{"crate_id":1,"path":["core","num","nonzero","NonZero"],"kind":"struct"},"1:48280:3300":{"crate_id":1,"path":["core","core_arch","simd","i64x8"],"kind":"struct"},"1:41527:3460":{"crate_id":1,"path":["core","iter","sources","successors","Successors"],"kind":"struct"},"1:22407:1836":{"crate_id":1,"path":["core","core_simd","simd","num","sealed","Sealed"],"kind":"trait"},"1:44463:2512":{"crate_id":1,"path":["core","str","iter","EscapeDefault"],"kind":"struct"},"1:10060:2162":{"crate_id":1,"path":["core","fmt","UpperHex"],"kind":"trait"},"1:3046:3569":{"crate_id":1,"path":["core","ops","arith","Sub"],"kind":"trait"},"1:8415:2206":{"crate_id":1,"path":["core","iter","traits","marker","TrustedLen"],"kind":"trait"},"1:40657:2512":{"crate_id":1,"path":["core","ascii","EscapeDefault"],"kind":"struct"},"1:10054:2159":{"crate_id":1,"path":["core","fmt","Octal"],"kind":"trait"},"1:40886:3851":{"crate_id":1,"path":["core","ffi","VaList"],"kind":"struct"},"1:42272:194":{"crate_id":1,"path":["core","option","Option"],"kind":"enum"},"1:3220:2209":{"crate_id":1,"path":["core","ops","deref","DerefMut"],"kind":"trait"},"1:10938:2415":{"crate_id":1,"path":["core","slice","iter","SplitInclusive"],"kind":"struct"},"1:8103:179":{"crate_id":1,"path":["core","iter","traits","iterator","Iterator"],"kind":"trait"},"1:2995:246":{"crate_id":1,"path":["core","marker","Sync"],"kind":"trait"},"1:46352:3221":{"crate_id":1,"path":["core","core_arch","simd","i32x2"],"kind":"struct"},"1:44714:3491":{"crate_id":1,"path":["core","str","pattern","StrSearcher"],"kind":"struct"},"1:43001:2159":{"crate_id":1,"path":["core","fmt","num","Octal"],"kind":"struct"},"1:45064:150":{"crate_id":1,"path":["core","future","future","Future"],"kind":"trait"},"1:44945:3506":{"crate_id":1,"path":["core","time","TryFromFloatSecsError"],"kind":"struct"},"1:44585:3486":{"crate_id":1,"path":["core","str","pattern","CharArraySearcher"],"kind":"struct"},"1:6447:3379":{"crate_id":1,"path":["core","iter","adapters","intersperse","IntersperseWith"],"kind":"struct"},"1:21458:12352":{"crate_id":1,"path":["core","core_simd","swizzle","resize","Resize"],"kind":"struct"},"1:3041:3567":{"crate_id":1,"path":["core","ops","arith","Add"],"kind":"trait"},"1:10373:1517":{"crate_id":1,"path":["core","slice"],"kind":"module"},"1:42178:10067":{"crate_id":1,"path":["core","net","parser","AddrKind"],"kind":"enum"},"1:4354:2781":{"crate_id":1,"path":["core","cell","lazy","LazyCell"],"kind":"struct"},"1:22521:1836":{"crate_id":1,"path":["core","core_simd","simd","ptr","sealed","Sealed"],"kind":"trait"},"1:4:1125":{"crate_id":1,"path":["core","panic"],"kind":"macro"},"1:6642:3385":{"crate_id":1,"path":["core","iter","adapters","map_windows","MapWindowsInner"],"kind":"struct"},"1:44030:2410":{"crate_id":1,"path":["core","slice","iter","ArrayChunks"],"kind":"struct"},"1:48403:3306":{"crate_id":1,"path":["core","core_arch","x86","__m256i"],"kind":"struct"},"1:2990:119":{"crate_id":1,"path":["core","marker","Copy"],"kind":"trait"},"1:9711:2800":{"crate_id":1,"path":["core","fmt","builders","PadAdapterState"],"kind":"struct"},"1:42066:3879":{"crate_id":1,"path":["core","net","ip_addr","Ipv6MulticastScope"],"kind":"enum"},"1:44762:2490":{"crate_id":1,"path":["core","str","lossy","Utf8Chunk"],"kind":"struct"},"0:28:1833":{"crate_id":0,"path":["itoa","Integer"],"kind":"trait"},"1:30997:10059":{"crate_id":1,"path":["core","ptr","alignment","AlignmentEnum16"],"kind":"enum"},"1:7384:3872":{"crate_id":1,"path":["core","iter","adapters","zip","TrustedRandomAccess"],"kind":"trait"},"1:46866:3241":{"crate_id":1,"path":["core","core_arch","simd","m16x8"],"kind":"struct"},"1:2835:138":{"crate_id":1,"path":["core","error","Error"],"kind":"trait"},"1:2740:78":{"crate_id":1,"path":["core","convert","AsRef"],"kind":"trait"},"1:22787:2814":{"crate_id":1,"path":["core","num","dec2flt","number","Number"],"kind":"struct"},"1:44447:2510":{"crate_id":1,"path":["core","str","iter","EncodeUtf16"],"kind":"struct"},"1:42777:96":{"crate_id":1,"path":["core","sync","atomic","AtomicU64"],"kind":"struct"},"1:22921:3400":{"crate_id":1,"path":["core","num","fmt","Formatted"],"kind":"struct"},"1:40742:2512":{"crate_id":1,"path":["core","char","EscapeDefault"],"kind":"struct"},"1:40734:2513":{"crate_id":1,"path":["core","char","EscapeUnicode"],"kind":"struct"},"1:21661:9005":{"crate_id":1,"path":["core","core_simd","lane_count","SupportedLaneCount"],"kind":"trait"},"1:40955:2789":{"crate_id":1,"path":["core","iter","adapters","cloned","Cloned"],"kind":"struct"},"1:53618:803":{"crate_id":1,"path":["core","i32"],"kind":"primitive"},"1:22879:10062":{"crate_id":1,"path":["core","num","flt2dec","Sign"],"kind":"enum"},"1:39922:210":{"crate_id":1,"path":["core","ops","range","Range"],"kind":"struct"},"1:40906:3854":{"crate_id":1,"path":["core","io","borrowed_buf","BorrowedCursor"],"kind":"struct"},"1:42094:2950":{"crate_id":1,"path":["core","net","ip_addr","fmt","Span"],"kind":"struct"},"1:44871:2480":{"crate_id":1,"path":["core","str","CharEscapeDebugContinue"],"kind":"struct"},"1:53607:1162":{"crate_id":1,"path":["core","pointer"],"kind":"primitive"},"1:53619:804":{"crate_id":1,"path":["core","i64"],"kind":"primitive"},"1:10263:153":{"crate_id":1,"path":["core","hash","Hash"],"kind":"trait"},"1:10693:1836":{"crate_id":1,"path":["core","slice","index","private_slice_index","Sealed"],"kind":"trait"},"1:46167:3214":{"crate_id":1,"path":["core","core_arch","simd","i16x2"],"kind":"struct"},"1:1948:2314":{"crate_id":1,"path":["core","ptr","metadata","DynMetadata"],"kind":"struct"},"1:43298:2169":{"crate_id":1,"path":["core","fmt","Alignment"],"kind":"enum"},"1:13426:117":{"crate_id":1,"path":["core","task","wake","Context"],"kind":"struct"},"1:23985:236":{"crate_id":1,"path":["core","num","saturating","Saturating"],"kind":"struct"},"1:45175:3208":{"crate_id":1,"path":["core","alloc","AllocError"],"kind":"struct"},"1:44739:3494":{"crate_id":1,"path":["core","str","pattern","EmptyNeedle"],"kind":"struct"},"1:26385:266":{"crate_id":1,"path":["core","num","wrapping","Wrapping"],"kind":"struct"},"1:22211:1836":{"crate_id":1,"path":["core","core_simd","vector","sealed","Sealed"],"kind":"trait"},"1:12352:2520":{"crate_id":1,"path":["core","str","iter","SplitNInternal"],"kind":"struct"},"1:44749:3498":{"crate_id":1,"path":["core","str","pattern","TwoWaySearcher"],"kind":"struct"},"1:1925:2315":{"crate_id":1,"path":["core","ptr","metadata","Pointee"],"kind":"trait"},"1:44377:2507":{"crate_id":1,"path":["core","str","iter","RMatches"],"kind":"struct"},"1:9202:2486":{"crate_id":1,"path":["core","panicking","assert_matches_failed","Pattern"],"kind":"struct"},"1:12844:121":{"crate_id":1,"path":["core","str","lossy","Debug"],"kind":"struct"},"1:40022:2388":{"crate_id":1,"path":["core","ops","range","Bound"],"kind":"enum"},"1:12127:2383":{"crate_id":1,"path":["core","slice","SlicePattern"],"kind":"trait"},"1:44556:3476":{"crate_id":1,"path":["core","str","pattern","CharSearcher"],"kind":"struct"},"1:44891:2484":{"crate_id":1,"path":["core","str","IsNotEmpty"],"kind":"struct"},"1:45126:3205":{"crate_id":1,"path":["core","task","wake","RawWakerVTable"],"kind":"struct"},"1:12315:2518":{"crate_id":1,"path":["core","str","iter","SplitInternal"],"kind":"struct"},"1:11050:2402":{"crate_id":1,"path":["core","slice","iter","RSplit"],"kind":"struct"},"1:41064:3438":{"crate_id":1,"path":["core","iter","adapters","map_while","MapWhile"],"kind":"struct"},"1:46300:3219":{"crate_id":1,"path":["core","core_arch","simd","i8x8"],"kind":"struct"},"1:53627:1708":{"crate_id":1,"path":["core","usize"],"kind":"primitive"},"1:2463:103":{"crate_id":1,"path":["core","borrow","Borrow"],"kind":"trait"},"1:2568:195":{"crate_id":1,"path":["core","cmp","Ord"],"kind":"trait"},"1:44101:2496":{"crate_id":1,"path":["core","str","error","Utf8Error"],"kind":"struct"},"1:3363:211":{"crate_id":1,"path":["core","ops","range","RangeBounds"],"kind":"trait"},"1:3037:2312":{"crate_id":1,"path":["core","marker","FnPtr"],"kind":"trait"},"2:0:481":{"crate_id":2,"path":["compiler_builtins"],"kind":"module"},"1:12633:2488":{"crate_id":1,"path":["core","str","pattern","ReverseSearcher"],"kind":"trait"},"1:7731:3802":{"crate_id":1,"path":["core","iter","sources","once","once"],"kind":"function"},"1:11656:2413":{"crate_id":1,"path":["core","slice","iter","ChunkBy"],"kind":"struct"},"1:43504:2954":{"crate_id":1,"path":["core","hash","sip","SipHasher24"],"kind":"struct"},"1:22436:2295":{"crate_id":1,"path":["core","core_simd","simd","ptr","const_ptr","SimdConstPtr","from_exposed_addr"],"kind":"function"},"1:46055:3209":{"crate_id":1,"path":["core","core_arch","simd","u8x2"],"kind":"struct"},"1:10846:2202":{"crate_id":1,"path":["core","slice","iter","Iter"],"kind":"struct"},"1:46370:3222":{"crate_id":1,"path":["core","core_arch","simd","i64x1"],"kind":"struct"},"1:11088:2403":{"crate_id":1,"path":["core","slice","iter","RSplitMut"],"kind":"struct"},"1:42321:174":{"crate_id":1,"path":["core","option","Item"],"kind":"struct"},"1:2876:3739":{"crate_id":1,"path":["core","error","Request"],"kind":"struct"},"1:47314:3262":{"crate_id":1,"path":["core","core_arch","simd","i16x16"],"kind":"struct"},"1:46075:3210":{"crate_id":1,"path":["core","core_arch","simd","i8x2"],"kind":"struct"},"1:43244:2169":{"crate_id":1,"path":["core","fmt","rt","Alignment"],"kind":"enum"},"1:42234:3173":{"crate_id":1,"path":["core","net","socket_addr","SocketAddrV4"],"kind":"struct"},"1:42621:94":{"crate_id":1,"path":["core","sync","atomic","AtomicU16"],"kind":"struct"},"1:41485:3455":{"crate_id":1,"path":["core","iter","sources","once","Once"],"kind":"struct"},"1:3056:3754":{"crate_id":1,"path":["core","ops","arith","Neg"],"kind":"trait"},"1:22434:11763":{"crate_id":1,"path":["core","core_simd","simd","ptr","const_ptr","SimdConstPtr","with_addr"],"kind":"function"},"1:43261:11643":{"crate_id":1,"path":["core","fmt","rt","Count"],"kind":"enum"},"1:44359:2506":{"crate_id":1,"path":["core","str","iter","Matches"],"kind":"struct"},"1:53625:1649":{"crate_id":1,"path":["core","u128"],"kind":"primitive"},"1:40783:3828":{"crate_id":1,"path":["core","char","CaseMappingIter"],"kind":"enum"},"1:53610:1549":{"crate_id":1,"path":["core","str"],"kind":"primitive"},"1:3231:2137":{"crate_id":1,"path":["core","ops","drop","Drop"],"kind":"trait"},"1:22383:9091":{"crate_id":1,"path":["core","core_simd","simd","num","uint","SimdUint"],"kind":"trait"},"1:40973:3427":{"crate_id":1,"path":["core","iter","adapters","cycle","Cycle"],"kind":"struct"},"1:40052:3777":{"crate_id":1,"path":["core","ops","try_trait","Yeet"],"kind":"struct"},"1:53602:404":{"crate_id":1,"path":["core","bool"],"kind":"primitive"},"1:32731:12329":{"crate_id":1,"path":["core","error","tags","Value"],"kind":"struct"},"1:42386:2195":{"crate_id":1,"path":["core","panic","panic_info","PanicInfo"],"kind":"struct"},"1:30933:2107":{"crate_id":1,"path":["core","mem","manually_drop","ManuallyDrop"],"kind":"struct"},"1:48383:3304":{"crate_id":1,"path":["core","core_arch","x86","__m128"],"kind":"struct"},"1:21600:1836":{"crate_id":1,"path":["core","core_simd","cast","sealed","Sealed"],"kind":"trait"},"1:22703:3397":{"crate_id":1,"path":["core","num","bignum","tests","Big8x3"],"kind":"struct"},"1:2749:145":{"crate_id":1,"path":["core","convert","From"],"kind":"trait"},"1:4682:2174":{"crate_id":1,"path":["core","cell","SyncUnsafeCell"],"kind":"struct"},"1:42415:226":{"crate_id":1,"path":["core","result","Result"],"kind":"enum"},"1:3849:2204":{"crate_id":1,"path":["core","array","iter","IntoIter"],"kind":"struct"},"1:2746:163":{"crate_id":1,"path":["core","convert","Into"],"kind":"trait"},"1:10058:2161":{"crate_id":1,"path":["core","fmt","LowerHex"],"kind":"trait"},"1:43289:74":{"crate_id":1,"path":["core","fmt","rt","Argument"],"kind":"struct"},"1:5039:12124":{"crate_id":1,"path":["core","ffi","sealed_trait","VaArgSafe"],"kind":"trait"},"1:45118:3977":{"crate_id":1,"path":["core","task","wake","RawWaker"],"kind":"struct"},"1:9091:2797":{"crate_id":1,"path":["core","panic","unwind_safe","AssertUnwindSafe"],"kind":"struct"},"1:10515:11603":{"crate_id":1,"path":["core","slice","sort","merge_sort","RunVec"],"kind":"struct"},"1:22213:9004":{"crate_id":1,"path":["core","core_simd","vector","SimdElement"],"kind":"trait"},"1:4428:2171":{"crate_id":1,"path":["core","cell","Cell"],"kind":"struct"},"1:45148:181":{"crate_id":1,"path":["core","alloc","layout","Layout"],"kind":"struct"},"1:48478:3311":{"crate_id":1,"path":["core","core_arch","x86","__m512d"],"kind":"struct"},"1:3130:3764":{"crate_id":1,"path":["core","ops","bit","Not"],"kind":"trait"},"1:12627:2489":{"crate_id":1,"path":["core","str","pattern","Searcher"],"kind":"trait"},"1:10895:2398":{"crate_id":1,"path":["core","slice","iter","Split"],"kind":"struct"},"1:4655:2175":{"crate_id":1,"path":["core","cell","UnsafeCell"],"kind":"struct"},"1:12143:2385":{"crate_id":1,"path":["core","slice","GetManyMutError"],"kind":"struct"},"1:22928:3080":{"crate_id":1,"path":["core","num","error","TryFromIntError"],"kind":"struct"},"1:3466:11627":{"crate_id":1,"path":["core","ops","try_trait","NeverShortCircuitResidual"],"kind":"enum"},"1:8459:12246":{"crate_id":1,"path":["core","net","display_buffer","DisplayBuffer"],"kind":"struct"},"1:47424:3265":{"crate_id":1,"path":["core","core_arch","simd","f32x8"],"kind":"struct"},"1:3073:3773":{"crate_id":1,"path":["core","ops","async_function","AsyncFnMut"],"kind":"trait"},"1:44899:2479":{"crate_id":1,"path":["core","str","UnsafeBytesToStr"],"kind":"struct"},"1:15:1834":{"crate_id":1,"path":["core","write"],"kind":"macro"},"1:3270:3776":{"crate_id":1,"path":["core","ops","index","IndexMut"],"kind":"trait"},"1:11129:2400":{"crate_id":1,"path":["core","slice","iter","SplitN"],"kind":"struct"},"1:44887:2483":{"crate_id":1,"path":["core","str","IsAsciiWhitespace"],"kind":"struct"},"1:32761:237":{"crate_id":1,"path":["core","marker","Send"],"kind":"trait"},"1:44956:3952":{"crate_id":1,"path":["core","time","TryFromFloatSecsErrorKind"],"kind":"enum"},"1:41509:3459":{"crate_id":1,"path":["core","iter","sources","repeat_n","RepeatN"],"kind":"struct"},"1:32819:2948":{"crate_id":1,"path":["core","marker","PhantomPinned"],"kind":"struct"},"1:44875:2482":{"crate_id":1,"path":["core","str","CharEscapeUnicode"],"kind":"struct"},"1:1655:1814":{"crate_id":1,"path":["core","mem"],"kind":"module"},"1:46229:3216":{"crate_id":1,"path":["core","core_arch","simd","u16x4"],"kind":"struct"},"1:41077:3439":{"crate_id":1,"path":["core","iter","adapters","peekable","Peekable"],"kind":"struct"},"1:48172:3298":{"crate_id":1,"path":["core","core_arch","simd","u32x16"],"kind":"struct"},"1:44155:2398":{"crate_id":1,"path":["core","str","iter","Split"],"kind":"struct"},"0:14:1823":{"crate_id":0,"path":["itoa","Buffer"],"kind":"struct"},"1:43736:3199":{"crate_id":1,"path":["core","slice","sort","TimSortRun"],"kind":"struct"},"1:3453:3780":{"crate_id":1,"path":["core","ops","try_trait","NeverShortCircuit"],"kind":"struct"},"1:44075:2407":{"crate_id":1,"path":["core","slice","iter","RChunksExact"],"kind":"struct"},"1:43904:11557":{"crate_id":1,"path":["core","slice","iter","GenericSplitN"],"kind":"struct"},"1:46897:3242":{"crate_id":1,"path":["core","core_arch","simd","m32x4"],"kind":"struct"},"1:40674:3412":{"crate_id":1,"path":["core","char","convert","ParseCharError"],"kind":"struct"},"1:32745:2172":{"crate_id":1,"path":["core","error","tags","Ref"],"kind":"struct"},"1:42818:91":{"crate_id":1,"path":["core","sync","atomic","AtomicIsize"],"kind":"struct"},"1:40815:107":{"crate_id":1,"path":["core","ffi","c_str","CStr"],"kind":"struct"},"1:41136:3446":{"crate_id":1,"path":["core","iter","adapters","step_by","StepBy"],"kind":"struct"},"1:46389:3223":{"crate_id":1,"path":["core","core_arch","simd","f32x2"],"kind":"struct"},"1:44429:2502":{"crate_id":1,"path":["core","str","iter","SplitWhitespace"],"kind":"struct"},"1:53617:802":{"crate_id":1,"path":["core","i16"],"kind":"primitive"},"1:4220:11801":{"crate_id":1,"path":["core","asserting","TryCaptureWithoutDebug"],"kind":"struct"},"1:40933:3870":{"crate_id":1,"path":["core","iter","adapters","by_ref_sized","ByRefSized"],"kind":"struct"},"1:22299:9089":{"crate_id":1,"path":["core","core_simd","simd","num","float","SimdFloat"],"kind":"trait"},"1:46454:3225":{"crate_id":1,"path":["core","core_arch","simd","u8x16"],"kind":"struct"},"1:32762:2140":{"crate_id":1,"path":["core","marker","Sized"],"kind":"trait"},"1:43273:11640":{"crate_id":1,"path":["core","fmt","rt","Flag"],"kind":"enum"},"1:2824:126":{"crate_id":1,"path":["core","default","Default"],"kind":"trait"},"1:2137:2317":{"crate_id":1,"path":["core","ptr","unique","Unique"],"kind":"struct"},"1:46920:3243":{"crate_id":1,"path":["core","core_arch","simd","m64x2"],"kind":"struct"},"1:22059:1836":{"crate_id":1,"path":["core","core_simd","to_bytes","sealed","Sealed"],"kind":"trait"},"1:4143:3792":{"crate_id":1,"path":["core","array","Guard"],"kind":"struct"},"1:42896:2951":{"crate_id":1,"path":["core","sync","exclusive","Exclusive"],"kind":"struct"},"1:7919:3868":{"crate_id":1,"path":["core","iter","traits","accum","Product"],"kind":"trait"},"1:44114:2495":{"crate_id":1,"path":["core","str","error","ParseBoolError"],"kind":"struct"},"1:53626:856":{"crate_id":1,"path":["core","isize"],"kind":"primitive"},"1:42504:90":{"crate_id":1,"path":["core","sync","atomic","AtomicI8"],"kind":"struct"},"1:48032:3296":{"crate_id":1,"path":["core","core_arch","simd","u16x32"],"kind":"struct"},"1:48455:3310":{"crate_id":1,"path":["core","core_arch","x86","__m512"],"kind":"struct"},"1:43512:2955":{"crate_id":1,"path":["core","hash","sip","SipHasher"],"kind":"struct"},"1:44259:2400":{"crate_id":1,"path":["core","str","iter","SplitN"],"kind":"struct"},"1:21653:1836":{"crate_id":1,"path":["core","core_simd","lane_count","sealed","Sealed"],"kind":"trait"},"1:34563:3763":{"crate_id":1,"path":["core","ops","bit","BitXor"],"kind":"trait"},"1:2574:202":{"crate_id":1,"path":["core","cmp","PartialOrd"],"kind":"trait"},"1:41043:3436":{"crate_id":1,"path":["core","iter","adapters","intersperse","Intersperse"],"kind":"struct"},"1:10306:3910":{"crate_id":1,"path":["core","hash","BuildHasher"],"kind":"trait"},"1:46768:3239":{"crate_id":1,"path":["core","core_arch","simd","f64x4"],"kind":"struct"},"1:53609:1517":{"crate_id":1,"path":["core","slice"],"kind":"primitive"},"1:47780:3294":{"crate_id":1,"path":["core","core_arch","simd","u8x64"],"kind":"struct"},"1:47360:3263":{"crate_id":1,"path":["core","core_arch","simd","i32x8"],"kind":"struct"},"1:48531:3314":{"crate_id":1,"path":["core","core_arch","x86","__m512bh"],"kind":"struct"},"1:22771:2776":{"crate_id":1,"path":["core","num","dec2flt","decimal","Decimal"],"kind":"struct"},"1:42994:2160":{"crate_id":1,"path":["core","fmt","num","Binary"],"kind":"struct"},"1:10064:2163":{"crate_id":1,"path":["core","fmt","LowerExp"],"kind":"trait"},"1:39847:3782":{"crate_id":1,"path":["core","ops","coroutine","CoroutineState"],"kind":"enum"},"1:48318:3301":{"crate_id":1,"path":["core","core_arch","simd","u64x8"],"kind":"struct"},"2:234:226":{"crate_id":2,"path":["compiler_builtins","float","cmp","Result"],"kind":"enum"},"1:44205:2505":{"crate_id":1,"path":["core","str","iter","SplitTerminator"],"kind":"struct"},"1:44173:2402":{"crate_id":1,"path":["core","str","iter","RSplit"],"kind":"struct"},"1:42455:2202":{"crate_id":1,"path":["core","result","Iter"],"kind":"struct"},"1:40700:3156":{"crate_id":1,"path":["core","char","convert","CharTryFromError"],"kind":"struct"},"1:22756:2813":{"crate_id":1,"path":["core","num","dec2flt","common","BiasedFp"],"kind":"struct"},"1:46646:3234":{"crate_id":1,"path":["core","core_arch","simd","i16x8"],"kind":"struct"},"1:4498:221":{"crate_id":1,"path":["core","cell","RefCell"],"kind":"struct"},"1:53616:805":{"crate_id":1,"path":["core","i8"],"kind":"primitive"},"1:41494:3456":{"crate_id":1,"path":["core","iter","sources","once_with","OnceWith"],"kind":"struct"},"1:9524:92":{"crate_id":1,"path":["core","sync","atomic","AtomicPtr"],"kind":"struct"},"1:53629:13":{"crate_id":1,"path":["core","fn"],"kind":"primitive"},"1:40820:3422":{"crate_id":1,"path":["core","ffi","c_str","FromBytesWithNulError"],"kind":"struct"},"1:46819:3240":{"crate_id":1,"path":["core","core_arch","simd","m8x16"],"kind":"struct"},"1:46269:3218":{"crate_id":1,"path":["core","core_arch","simd","u64x1"],"kind":"struct"},"1:43973:2394":{"crate_id":1,"path":["core","slice","iter","ChunksMut"],"kind":"struct"},"1:21655:9002":{"crate_id":1,"path":["core","core_simd","lane_count","LaneCount"],"kind":"struct"},"1:3447:3778":{"crate_id":1,"path":["core","ops","try_trait","Residual"],"kind":"trait"},"1:48440:3309":{"crate_id":1,"path":["core","core_arch","x86","__m512i"],"kind":"struct"},"1:3189:3781":{"crate_id":1,"path":["core","ops","coroutine","Coroutine"],"kind":"trait"},"1:46199:3215":{"crate_id":1,"path":["core","core_arch","simd","u8x8"],"kind":"struct"},"1:22064:9008":{"crate_id":1,"path":["core","core_simd","to_bytes","ToBytes"],"kind":"trait"},"1:47078:3258":{"crate_id":1,"path":["core","core_arch","simd","u16x16"],"kind":"struct"},"1:2752:257":{"crate_id":1,"path":["core","convert","TryInto"],"kind":"trait"},"1:34021:3757":{"crate_id":1,"path":["core","ops","arith","DivAssign"],"kind":"trait"},"1:40059:3152":{"crate_id":1,"path":["core","any","TypeId"],"kind":"struct"},"1:34080:3759":{"crate_id":1,"path":["core","ops","arith","RemAssign"],"kind":"trait"},"1:41002:3431":{"crate_id":1,"path":["core","iter","adapters","filter_map","FilterMap"],"kind":"struct"},"1:10047:121":{"crate_id":1,"path":["core","fmt","Debug"],"kind":"trait"},"1:9519:85":{"crate_id":1,"path":["core","sync","atomic","AtomicBool"],"kind":"struct"},"1:21783:2812":{"crate_id":1,"path":["core","core_simd","masks","Mask"],"kind":"struct"},"1:33424:3753":{"crate_id":1,"path":["core","ops","arith","Div"],"kind":"trait"},"1:7279:2233":{"crate_id":1,"path":["core","iter","adapters","zip","zip"],"kind":"function"},"1:40831:10069":{"crate_id":1,"path":["core","ffi","c_str","FromBytesWithNulErrorKind"],"kind":"enum"},"1:21781:9003":{"crate_id":1,"path":["core","core_simd","masks","MaskElement"],"kind":"trait"},"1:43533:3195":{"crate_id":1,"path":["core","hash","sip","State"],"kind":"struct"},"1:41471:3453":{"crate_id":1,"path":["core","iter","sources","from_coroutine","FromCoroutine"],"kind":"struct"},"1:3030:3745":{"crate_id":1,"path":["core","marker","Freeze"],"kind":"trait"},"1:39232:3771":{"crate_id":1,"path":["core","ops","bit","ShrAssign"],"kind":"trait"},"1:41500:3457":{"crate_id":1,"path":["core","iter","sources","repeat","Repeat"],"kind":"struct"},"1:42034:3163":{"crate_id":1,"path":["core","net","ip_addr","Ipv4Addr"],"kind":"struct"},"1:40750:2511":{"crate_id":1,"path":["core","char","EscapeDebug"],"kind":"struct"},"1:10066:2164":{"crate_id":1,"path":["core","fmt","UpperExp"],"kind":"trait"},"1:33238:3568":{"crate_id":1,"path":["core","ops","arith","Mul"],"kind":"trait"},"1:41126:3444":{"crate_id":1,"path":["core","iter","adapters","skip_while","SkipWhile"],"kind":"struct"},"1:44535:3941":{"crate_id":1,"path":["core","str","pattern","SearchStep"],"kind":"enum"},"1:8047:2138":{"crate_id":1,"path":["core","iter","traits","exact_size","ExactSizeIterator"],"kind":"trait"},"1:6018:2793":{"crate_id":1,"path":["core","iter","adapters","flatten","Flatten"],"kind":"struct"},"1:4581:2172":{"crate_id":1,"path":["core","cell","Ref"],"kind":"struct"},"1:40802:3157":{"crate_id":1,"path":["core","char","TryFromCharError"],"kind":"struct"},"1:33903:3760":{"crate_id":1,"path":["core","ops","arith","SubAssign"],"kind":"trait"},"1:4571:3371":{"crate_id":1,"path":["core","cell","BorrowRef"],"kind":"struct"},"1:7956:166":{"crate_id":1,"path":["core","iter","traits","collect","IntoIterator"],"kind":"trait"},"1:21772:1836":{"crate_id":1,"path":["core","core_simd","masks","sealed","Sealed"],"kind":"trait"},"1:13554:3980":{"crate_id":1,"path":["core","alloc","Allocator"],"kind":"trait"},"1:53628:1259":{"crate_id":1,"path":["core","reference"],"kind":"primitive"},"1:22101:12355":{"crate_id":1,"path":["core","core_simd","vector","splat","Splat"],"kind":"struct"},"1:44879:2481":{"crate_id":1,"path":["core","str","CharEscapeDefault"],"kind":"struct"},"1:53622:1650":{"crate_id":1,"path":["core","u16"],"kind":"primitive"},"1:41096:3441":{"crate_id":1,"path":["core","iter","adapters","scan","Scan"],"kind":"struct"},"1:3518:3784":{"crate_id":1,"path":["core","ops","unsize","DispatchFromDyn"],"kind":"trait"},"1:41087:2795":{"crate_id":1,"path":["core","iter","adapters","rev","Rev"],"kind":"struct"},"1:43993:2405":{"crate_id":1,"path":["core","slice","iter","ChunksExactMut"],"kind":"struct"},"1:1729:3792":{"crate_id":1,"path":["core","mem","maybe_uninit","clone_from_slice","Guard"],"kind":"struct"},"1:10703:239":{"crate_id":1,"path":["core","slice","index","SliceIndex"],"kind":"trait"},"1:5733:3792":{"crate_id":1,"path":["core","iter","adapters","filter","next_chunk","Guard"],"kind":"struct"},"1:32752:3407":{"crate_id":1,"path":["core","error","Source"],"kind":"struct"},"1:44650:3489":{"crate_id":1,"path":["core","str","pattern","CharSliceSearcher"],"kind":"struct"},"1:13250:12415":{"crate_id":1,"path":["core","future","join","MaybeDone"],"kind":"enum"},"1:39895:3409":{"crate_id":1,"path":["core","ops","index_range","IndexRange"],"kind":"struct"},"1:42355:2194":{"crate_id":1,"path":["core","panic","location","Location"],"kind":"struct"},"1:53614:698":{"crate_id":1,"path":["core","f32"],"kind":"primitive"},"1:42543:97":{"crate_id":1,"path":["core","sync","atomic","AtomicU8"],"kind":"struct"},"1:46722:3237":{"crate_id":1,"path":["core","core_arch","simd","f32x4"],"kind":"struct"},"1:36612:3766":{"crate_id":1,"path":["core","ops","bit","Shr"],"kind":"trait"},"1:43551:2957":{"crate_id":1,"path":["core","hash","sip","Sip24Rounds"],"kind":"struct"},"1:3000:2177":{"crate_id":1,"path":["core","marker","PhantomData"],"kind":"struct"},"1:46530:3231":{"crate_id":1,"path":["core","core_arch","simd","u32x4"],"kind":"struct"},"1:53603:1044":{"crate_id":1,"path":["core","never"],"kind":"primitive"},"1:47574:3266":{"crate_id":1,"path":["core","core_arch","simd","i8x64"],"kind":"struct"},"1:21446:12357":{"crate_id":1,"path":["core","core_simd","swizzle","deinterleave","Odd"],"kind":"struct"},"1:22821:10056":{"crate_id":1,"path":["core","num","dec2flt","FloatErrorKind"],"kind":"enum"},"1:4267:3799":{"crate_id":1,"path":["core","async_iter","async_iter","AsyncIterator"],"kind":"trait"},"1:3715:9578":{"crate_id":1,"path":["core","array","drain","Drain"],"kind":"struct"},"1:44056:2406":{"crate_id":1,"path":["core","slice","iter","RChunks"],"kind":"struct"},"1:40757:3827":{"crate_id":1,"path":["core","char","EscapeDebugInner"],"kind":"enum"},"1:42857:98":{"crate_id":1,"path":["core","sync","atomic","AtomicUsize"],"kind":"struct"},"1:41519:3158":{"crate_id":1,"path":["core","iter","sources","repeat_with","RepeatWith"],"kind":"struct"},"1:42480:196":{"crate_id":1,"path":["core","sync","atomic","Ordering"],"kind":"enum"},"1:40002:216":{"crate_id":1,"path":["core","ops","range","RangeToInclusive"],"kind":"struct"},"1:40983:2792":{"crate_id":1,"path":["core","iter","adapters","enumerate","Enumerate"],"kind":"struct"},"1:45067:219":{"crate_id":1,"path":["core","future","ready","Ready"],"kind":"struct"},"1:22570:9083":{"crate_id":1,"path":["core","core_simd","simd","cmp","ord","SimdOrd"],"kind":"trait"},"1:22344:9090":{"crate_id":1,"path":["core","core_simd","simd","num","int","SimdInt"],"kind":"trait"},"1:5077:3853":{"crate_id":1,"path":["core","io","borrowed_buf","BorrowedBuf"],"kind":"struct"},"1:47154:3260":{"crate_id":1,"path":["core","core_arch","simd","u64x4"],"kind":"struct"},"1:47000:3244":{"crate_id":1,"path":["core","core_arch","simd","u8x32"],"kind":"struct"},"1:4385:2782":{"crate_id":1,"path":["core","cell","once","OnceCell"],"kind":"struct"},"1:43234:3182":{"crate_id":1,"path":["core","fmt","rt","Placeholder"],"kind":"struct"},"1:31535:2819":{"crate_id":1,"path":["core","cmp","Reverse"],"kind":"struct"},"1:42050:3165":{"crate_id":1,"path":["core","net","ip_addr","Ipv6Addr"],"kind":"struct"},"1:40942:2784":{"crate_id":1,"path":["core","iter","adapters","chain","Chain"],"kind":"struct"},"1:39891:3775":{"crate_id":1,"path":["core","ops","index","Index"],"kind":"trait"},"1:13228:165":{"crate_id":1,"path":["core","future","into_future","IntoFuture"],"kind":"trait"},"1:38543:3768":{"crate_id":1,"path":["core","ops","bit","BitOrAssign"],"kind":"trait"},"1:12618:2486":{"crate_id":1,"path":["core","str","pattern","Pattern"],"kind":"trait"},"1:21674:2812":{"crate_id":1,"path":["core","core_simd","masks","mask_impl","Mask"],"kind":"struct"},"1:46330:3220":{"crate_id":1,"path":["core","core_arch","simd","i16x4"],"kind":"struct"},"1:10483:12093":{"crate_id":1,"path":["core","slice","sort","merge","MergeHole"],"kind":"struct"},"1:42338:2203":{"crate_id":1,"path":["core","option","IterMut"],"kind":"struct"},"1:2379:2295":{"crate_id":1,"path":["core","ptr","from_exposed_addr"],"kind":"function"},"1:4635:2173":{"crate_id":1,"path":["core","cell","RefMut"],"kind":"struct"},"1:34390:3762":{"crate_id":1,"path":["core","ops","bit","BitOr"],"kind":"trait"},"1:42200:3468":{"crate_id":1,"path":["core","net","parser","AddrParseError"],"kind":"struct"},"1:7965:2139":{"crate_id":1,"path":["core","iter","traits","collect","Extend"],"kind":"trait"},"1:22859:10060":{"crate_id":1,"path":["core","num","flt2dec","decoder","FullDecoded"],"kind":"enum"},"1:42471:2204":{"crate_id":1,"path":["core","result","IntoIter"],"kind":"struct"},"1:12375:2517":{"crate_id":1,"path":["core","str","iter","MatchIndicesInternal"],"kind":"struct"},"1:7915:3869":{"crate_id":1,"path":["core","iter","traits","accum","Sum"],"kind":"trait"},"1:44921:132":{"crate_id":1,"path":["core","time","Duration"],"kind":"struct"},"1:12429:2415":{"crate_id":1,"path":["core","str","iter","SplitInclusive"],"kind":"struct"},"1:44305:2508":{"crate_id":1,"path":["core","str","iter","MatchIndices"],"kind":"struct"},"1:32818:2141":{"crate_id":1,"path":["core","marker","Unpin"],"kind":"trait"},"1:33844:3756":{"crate_id":1,"path":["core","ops","arith","AddAssign"],"kind":"trait"},"1:22089:2391":{"crate_id":1,"path":["core","core_simd","vector","Simd"],"kind":"struct"},"1:41011:3432":{"crate_id":1,"path":["core","iter","adapters","flatten","FlattenCompat"],"kind":"struct"},"1:13277:205":{"crate_id":1,"path":["core","future","pending","Pending"],"kind":"struct"},"1:22894:10074":{"crate_id":1,"path":["core","num","fmt","Part"],"kind":"enum"},"1:2988:3744":{"crate_id":1,"path":["core","marker","Unsize"],"kind":"trait"},"1:32689:3734":{"crate_id":1,"path":["core","convert","Infallible"],"kind":"enum"},"1:1853:1200":{"crate_id":1,"path":["core","ptr"],"kind":"module"},"1:11015:2416":{"crate_id":1,"path":["core","slice","iter","SplitInclusiveMut"],"kind":"struct"},"1:42397:3884":{"crate_id":1,"path":["core","panic","unwind_safe","RefUnwindSafe"],"kind":"trait"},"1:53621:1653":{"crate_id":1,"path":["core","u8"],"kind":"primitive"},"1:1823:2103":{"crate_id":1,"path":["core","mem","Discriminant"],"kind":"struct"},"1:32850:116":{"crate_id":1,"path":["core","marker","ConstParamTy"],"kind":"trait"},"1:3426:2389":{"crate_id":1,"path":["core","ops","range","OneSidedRange"],"kind":"trait"},"1:3238:142":{"crate_id":1,"path":["core","ops","function","FnMut"],"kind":"trait"},"1:53604:454":{"crate_id":1,"path":["core","char"],"kind":"primitive"},"1:46251:3217":{"crate_id":1,"path":["core","core_arch","simd","u32x2"],"kind":"struct"},"1:725:1836":{"crate_id":1,"path":["core","num","nonzero","private","Sealed"],"kind":"trait"},"1:39944:212":{"crate_id":1,"path":["core","ops","range","RangeFrom"],"kind":"struct"},"1:10056:2160":{"crate_id":1,"path":["core","fmt","Binary"],"kind":"trait"},"1:44409:2501":{"crate_id":1,"path":["core","str","iter","Lines"],"kind":"struct"}},"external_crates":{"1":{"name":"core","html_root_url":"https://doc.rust-lang.org/nightly/"},"2":{"name":"compiler_builtins","html_root_url":"https://doc.rust-lang.org/nightly/"},"3":{"name":"rustc_std_workspace_core","html_root_url":"https://doc.rust-lang.org/nightly/"}},"format_version":28}